FATtools/FAT.py
FATtools/Volume.py
FATtools/__init__.py
FATtools/crc32c.py
FATtools/debug.py
FATtools/disk.py
FATtools/exFAT.py
FATtools/gptutils.py
FATtools/mkfat.py
FATtools/partutils.py
FATtools/utils.py
FATtools/vdiutils.py
FATtools/version.py
FATtools/vhdutils.py
FATtools/vhdxlog.py
FATtools/vhdxutils.py
FATtools/vmdkutils.py
FATtools/win32enumvols.py
FATtools/NTFS/Attribute.py
FATtools/NTFS/Boot.py
FATtools/NTFS/Commons.py
FATtools/NTFS/DatarunStream.py
FATtools/NTFS/Index.py
FATtools/NTFS/Record.py
FATtools/NTFS/Utils.py
FATtools/NTFS/__init__.py
FATtools/scripts/cat.py
FATtools/scripts/cp.py
FATtools/scripts/imgclone.py
FATtools/scripts/ls.py
FATtools/scripts/main.py
FATtools/scripts/mkfat.py
FATtools/scripts/mkvdisk.py
FATtools/scripts/reordergui.py
FATtools/scripts/rm.py
FATtools/scripts/wipe.py
fattools-1.1.7.dist-info/METADATA
fattools-1.1.7.dist-info/WHEEL
fattools-1.1.7.dist-info/entry_points.txt
fattools-1.1.7.dist-info/top_level.txt
fattools-1.1.7.dist-info/RECORD
