Metadata-Version: 2.4
Name: FATtools
Version: 1.1.7
Summary: Pure python tools for accessing FAT filesystem images and disks
Author-email: maxpat78 <maxpat78@yahoo.it>
License: GPL
Project-URL: homepage, https://github.com/maxpat78/FATtools
Project-URL: repository, https://github.com/maxpat78/FATtools.git
Keywords: FAT,disk,image
Classifier: Programming Language :: Python :: 3
Classifier: Intended Audience :: Developers
Classifier: Intended Audience :: System Administrators
Classifier: Environment :: Win32 (MS Windows)
Classifier: Environment :: MacOS X
Classifier: License :: OSI Approved :: GNU General Public License v3 (GPLv3)
Classifier: Operating System :: Microsoft :: Windows
Classifier: Operating System :: POSIX :: Linux
Classifier: Operating System :: MacOS :: MacOS X
Classifier: Topic :: System :: Filesystems
Requires-Python: >=3.5
Requires-Dist: hexdump
